<?xml version="1.0" encoding="utf-8"?>
<Directory Name="ped">
  <File Name="ugf_a_ceiling_frame_corner_4m_a_lod1.cgf" CRC32="0xC868BFD6" Size="144" CompressionType="100" Encrypted="False" />
  <File Name="ugf_a_ceiling_frame_corner_4m_a_lod1.cgfm" CRC32="0x3BB019C7" Size="62048" CompressionType="100" Encrypted="False" />
  <File Name="ugf_a_ceiling_frame_corner_4m_a_lod2.cgf" CRC32="0xF0C52E6A" Size="144" CompressionType="100" Encrypted="False" />
  <File Name="ugf_a_ceiling_frame_corner_4m_a_lod2.cgfm" CRC32="0x0967905C" Size="38816" CompressionType="100" Encrypted="False" />
  <File Name="ugf_a_ceiling_frame_corner_4m_a_lod3.cgf" CRC32="0x3DA2E0EE" Size="144" CompressionType="100" Encrypted="False" />
  <File Name="ugf_a_ceiling_frame_corner_4m_a_lod3.cgfm" CRC32="0x5CA601FD" Size="34520" CompressionType="100" Encrypted="False" />
  <File Name="ugf_a_ceiling_frame_corner_4m_a_lod4.cgf" CRC32="0xDCAA45B3" Size="144" CompressionType="100" Encrypted="False" />
  <File Name="ugf_a_ceiling_frame_corner_4m_a_lod4.cgfm" CRC32="0x97DD54C4" Size="15160" CompressionType="100" Encrypted="False" />
  <File Name="ugf_a_ceiling_frame_corner_4m_a_lod5.cgf" CRC32="0xC9E874F1" Size="144" CompressionType="100" Encrypted="False" />
  <File Name="ugf_a_ceiling_frame_corner_4m_a_lod5.cgfm" CRC32="0x85349914" Size="10952" CompressionType="100" Encrypted="False" />
  <File Name="ugf_a_ceiling_frame_corner_4m_a.cgf" CRC32="0xACF50E0B" Size="44200" CompressionType="100" Encrypted="False" />
  <File Name="ugf_a_ceiling_frame_corner_4m_a.cgfm" CRC32="0x794178FC" Size="191056" CompressionType="100" Encrypted="False" />
  <File Name="ugf_a_ceiling_frame_corner_5m_a_lod1.cgf" CRC32="0xE4389FAF" Size="144" CompressionType="100" Encrypted="False" />
  <File Name="ugf_a_ceiling_frame_corner_5m_a_lod1.cgfm" CRC32="0x7F8D8F22" Size="69624" CompressionType="100" Encrypted="False" />
  <File Name="ugf_a_ceiling_frame_corner_5m_a_lod2.cgf" CRC32="0xA52A2970" Size="144" CompressionType="100" Encrypted="False" />
  <File Name="ugf_a_ceiling_frame_corner_5m_a_lod2.cgfm" CRC32="0x6C49076F" Size="40584" CompressionType="100" Encrypted="False" />
  <File Name="ugf_a_ceiling_frame_corner_5m_a_lod3.cgf" CRC32="0xD371F629" Size="144" CompressionType="100" Encrypted="False" />
  <File Name="ugf_a_ceiling_frame_corner_5m_a_lod3.cgfm" CRC32="0xDF3D17D4" Size="33848" CompressionType="100" Encrypted="False" />
  <File Name="ugf_a_ceiling_frame_corner_5m_a_lod4.cgf" CRC32="0x1C30B083" Size="144" CompressionType="100" Encrypted="False" />
  <File Name="ugf_a_ceiling_frame_corner_5m_a_lod4.cgfm" CRC32="0x3F83F563" Size="14968" CompressionType="100" Encrypted="False" />
  <File Name="ugf_a_ceiling_frame_corner_5m_a_lod5.cgf" CRC32="0xDBABA26B" Size="144" CompressionType="100" Encrypted="False" />
  <File Name="ugf_a_ceiling_frame_corner_5m_a_lod5.cgfm" CRC32="0x6203FAAE" Size="12808" CompressionType="100" Encrypted="False" />
  <File Name="ugf_a_ceiling_frame_corner_5m_a.cgf" CRC32="0xB21E2C2B" Size="43504" CompressionType="100" Encrypted="False" />
  <File Name="ugf_a_ceiling_frame_corner_5m_a.cgfm" CRC32="0x28FAC257" Size="202944" CompressionType="100" Encrypted="False" />
  <File Name="ugf_a_ceiling_frame_single_3m_a.cgf" CRC32="0x0D1A96B2" Size="1504" CompressionType="100" Encrypted="False" />
  <File Name="ugf_a_ceiling_frame_single_3m_a.cgfm" CRC32="0xAFDED600" Size="1992" CompressionType="100" Encrypted="False" />
  <File Name="ugf_a_wall_grate_4m_a_lod1.cgf" CRC32="0xC7226219" Size="152" CompressionType="100" Encrypted="False" />
  <File Name="ugf_a_wall_grate_4m_a_lod1.cgfm" CRC32="0x8932BD75" Size="8824" CompressionType="100" Encrypted="False" />
  <File Name="ugf_a_wall_grate_4m_a_lod2.cgf" CRC32="0x5EAC11D1" Size="152" CompressionType="100" Encrypted="False" />
  <File Name="ugf_a_wall_grate_4m_a_lod2.cgfm" CRC32="0xC29051B6" Size="4120" CompressionType="100" Encrypted="False" />
  <File Name="ugf_a_wall_grate_4m_a.cgf" CRC32="0x7A8484FF" Size="2944" CompressionType="100" Encrypted="False" />
  <File Name="ugf_a_wall_grate_4m_a.cgfm" CRC32="0xE2C05C74" Size="12888" CompressionType="100" Encrypted="False" />
  <File Name="util_ugf_surf_ped_01_01_floor_a_lod1.cgf" CRC32="0x27DCBBC8" Size="192" CompressionType="100" Encrypted="False" />
  <File Name="util_ugf_surf_ped_01_01_floor_a_lod1.cgfm" CRC32="0xC240F95C" Size="21800" CompressionType="100" Encrypted="False" />
  <File Name="util_ugf_surf_ped_01_01_floor_a_lod2.cgf" CRC32="0x4364D82A" Size="176" CompressionType="100" Encrypted="False" />
  <File Name="util_ugf_surf_ped_01_01_floor_a_lod2.cgfm" CRC32="0xDAFA3441" Size="12208" CompressionType="100" Encrypted="False" />
  <File Name="util_ugf_surf_ped_01_01_floor_a_lod3.cgf" CRC32="0x07B01CBC" Size="152" CompressionType="100" Encrypted="False" />
  <File Name="util_ugf_surf_ped_01_01_floor_a_lod3.cgfm" CRC32="0xDB25CAFE" Size="4904" CompressionType="100" Encrypted="False" />
  <File Name="util_ugf_surf_ped_01_01_floor_a.cgf" CRC32="0x1CD3E181" Size="15288" CompressionType="100" Encrypted="False" />
  <File Name="util_ugf_surf_ped_01_01_floor_a.cgfm" CRC32="0xC00D2896" Size="44928" CompressionType="100" Encrypted="False" />
  <File Name="util_ugf_surf_ped_01_01_floor_b_lod1.cgf" CRC32="0x5F4F79B9" Size="144" CompressionType="100" Encrypted="False" />
  <File Name="util_ugf_surf_ped_01_01_floor_b_lod1.cgfm" CRC32="0x1FA16770" Size="3936" CompressionType="100" Encrypted="False" />
  <File Name="util_ugf_surf_ped_01_01_floor_b.cgf" CRC32="0x90247437" Size="3192" CompressionType="100" Encrypted="False" />
  <File Name="util_ugf_surf_ped_01_01_floor_b.cgfm" CRC32="0xB15640FF" Size="11184" CompressionType="100" Encrypted="False" />
  <File Name="util_ugf_surf_ped_ceiling_a_lod1.cgf" CRC32="0x31A671EF" Size="152" CompressionType="100" Encrypted="False" />
  <File Name="util_ugf_surf_ped_ceiling_a_lod1.cgfm" CRC32="0x13FA4578" Size="39288" CompressionType="100" Encrypted="False" />
  <File Name="util_ugf_surf_ped_ceiling_a_lod2.cgf" CRC32="0x6E03213F" Size="152" CompressionType="100" Encrypted="False" />
  <File Name="util_ugf_surf_ped_ceiling_a_lod2.cgfm" CRC32="0xFD075B26" Size="23488" CompressionType="100" Encrypted="False" />
  <File Name="util_ugf_surf_ped_ceiling_a_lod3.cgf" CRC32="0xEDA6500B" Size="152" CompressionType="100" Encrypted="False" />
  <File Name="util_ugf_surf_ped_ceiling_a_lod3.cgfm" CRC32="0x89179142" Size="19184" CompressionType="100" Encrypted="False" />
  <File Name="util_ugf_surf_ped_ceiling_a_lod4.cgf" CRC32="0xBF24C168" Size="152" CompressionType="100" Encrypted="False" />
  <File Name="util_ugf_surf_ped_ceiling_a_lod4.cgfm" CRC32="0xD896A6CA" Size="8208" CompressionType="100" Encrypted="False" />
  <File Name="util_ugf_surf_ped_ceiling_a.cgf" CRC32="0x45EB81FF" Size="24936" CompressionType="100" Encrypted="False" />
  <File Name="util_ugf_surf_ped_ceiling_a.cgfm" CRC32="0xC55156DD" Size="92840" CompressionType="100" Encrypted="False" />
  <File Name="util_ugf_surf_ped_floor_a_lod1.cgf" CRC32="0xBF22B728" Size="160" CompressionType="100" Encrypted="False" />
  <File Name="util_ugf_surf_ped_floor_a_lod1.cgfm" CRC32="0x3DDEC062" Size="9032" CompressionType="100" Encrypted="False" />
  <File Name="util_ugf_surf_ped_floor_a_lod2.cgf" CRC32="0xF585C055" Size="160" CompressionType="100" Encrypted="False" />
  <File Name="util_ugf_surf_ped_floor_a_lod2.cgfm" CRC32="0x2DA7AA0B" Size="4456" CompressionType="100" Encrypted="False" />
  <File Name="util_ugf_surf_ped_floor_a.cgf" CRC32="0x8B48A6A1" Size="7016" CompressionType="100" Encrypted="False" />
  <File Name="util_ugf_surf_ped_floor_a.cgfm" CRC32="0x275974CD" Size="21864" CompressionType="100" Encrypted="False" />
  <File Name="util_ugf_surf_ped_floor_b.cgf" CRC32="0x3AF717E6" Size="2176" CompressionType="100" Encrypted="False" />
  <File Name="util_ugf_surf_ped_floor_b.cgfm" CRC32="0x75806EBF" Size="4008" CompressionType="100" Encrypted="False" />
  <File Name="util_ugf_surf_ped_floor_c_lod1.cgf" CRC32="0xF99968E5" Size="152" CompressionType="100" Encrypted="False" />
  <File Name="util_ugf_surf_ped_floor_c_lod1.cgfm" CRC32="0xE9F53402" Size="32712" CompressionType="100" Encrypted="False" />
  <File Name="util_ugf_surf_ped_floor_c_lod2.cgf" CRC32="0xA24CA1EF" Size="152" CompressionType="100" Encrypted="False" />
  <File Name="util_ugf_surf_ped_floor_c_lod2.cgfm" CRC32="0x6FBE8E0B" Size="20112" CompressionType="100" Encrypted="False" />
  <File Name="util_ugf_surf_ped_floor_c_lod3.cgf" CRC32="0x2BD1BFF1" Size="152" CompressionType="100" Encrypted="False" />
  <File Name="util_ugf_surf_ped_floor_c_lod3.cgfm" CRC32="0x15754F3D" Size="14776" CompressionType="100" Encrypted="False" />
  <File Name="util_ugf_surf_ped_floor_c_lod4.cgf" CRC32="0xFA3FE693" Size="152" CompressionType="100" Encrypted="False" />
  <File Name="util_ugf_surf_ped_floor_c_lod4.cgfm" CRC32="0x3FBDE791" Size="6456" CompressionType="100" Encrypted="False" />
  <File Name="util_ugf_surf_ped_floor_c.cgf" CRC32="0x2F5F72FE" Size="25232" CompressionType="100" Encrypted="False" />
  <File Name="util_ugf_surf_ped_floor_c.cgfm" CRC32="0xD1DD7207" Size="87560" CompressionType="100" Encrypted="False" />
</Directory>