<?xml version="1.0" encoding="utf-8"?>
<Directory Name="unit">
  <File Name="bench_oza_a.cgf" CRC32="0x9DE1FD7B" Size="97968" CompressionType="100" Encrypted="False" />
  <File Name="bench_oza_a.cgfm" CRC32="0x28A025D5" Size="343592" CompressionType="100" Encrypted="False" />
  <File Name="unit_facade_frame_exterior_a_lod1.cgf" CRC32="0x4B255816" Size="104" CompressionType="100" Encrypted="False" />
  <File Name="unit_facade_frame_exterior_a_lod1.cgfm" CRC32="0xD956CB36" Size="33696" CompressionType="100" Encrypted="False" />
  <File Name="unit_facade_frame_exterior_a_lod2.cgf" CRC32="0xB5EBCADE" Size="104" CompressionType="100" Encrypted="False" />
  <File Name="unit_facade_frame_exterior_a_lod2.cgfm" CRC32="0x3E024042" Size="9728" CompressionType="100" Encrypted="False" />
  <File Name="unit_facade_frame_exterior_a_lod3.cgf" CRC32="0xB8640897" Size="104" CompressionType="100" Encrypted="False" />
  <File Name="unit_facade_frame_exterior_a_lod3.cgfm" CRC32="0xBA2B04A6" Size="5760" CompressionType="100" Encrypted="False" />
  <File Name="unit_facade_frame_exterior_a.cgf" CRC32="0xB083DE33" Size="25848" CompressionType="100" Encrypted="False" />
  <File Name="unit_facade_frame_exterior_a.cgfm" CRC32="0x0B6E3DB0" Size="68216" CompressionType="100" Encrypted="False" />
  <File Name="unit_oza_facade_a_alcove_a_glass_a_lod1.cgf" CRC32="0x5ECA3CA4" Size="104" CompressionType="100" Encrypted="False" />
  <File Name="unit_oza_facade_a_alcove_a_glass_a_lod1.cgfm" CRC32="0x085176FC" Size="52552" CompressionType="100" Encrypted="False" />
  <File Name="unit_oza_facade_a_alcove_a_glass_a_lod2.cgf" CRC32="0x120F3519" Size="104" CompressionType="100" Encrypted="False" />
  <File Name="unit_oza_facade_a_alcove_a_glass_a_lod2.cgfm" CRC32="0xBF50A753" Size="23272" CompressionType="100" Encrypted="False" />
  <File Name="unit_oza_facade_a_alcove_a_glass_a_lod3.cgf" CRC32="0x597D61DC" Size="104" CompressionType="100" Encrypted="False" />
  <File Name="unit_oza_facade_a_alcove_a_glass_a_lod3.cgfm" CRC32="0x3B7CC9BA" Size="2816" CompressionType="100" Encrypted="False" />
  <File Name="unit_oza_facade_a_alcove_a_glass_a.cgf" CRC32="0x28B5E1F4" Size="29240" CompressionType="100" Encrypted="False" />
  <File Name="unit_oza_facade_a_alcove_a_glass_a.cgfm" CRC32="0xA7BBD052" Size="100448" CompressionType="100" Encrypted="False" />
  <File Name="unit_oza_facade_interior_a_lod1.cgf" CRC32="0x5DD0940A" Size="104" CompressionType="100" Encrypted="False" />
  <File Name="unit_oza_facade_interior_a_lod1.cgfm" CRC32="0x6913693F" Size="209880" CompressionType="100" Encrypted="False" />
  <File Name="unit_oza_facade_interior_a_lod2.cgf" CRC32="0x4CC0A684" Size="104" CompressionType="100" Encrypted="False" />
  <File Name="unit_oza_facade_interior_a_lod2.cgfm" CRC32="0x9554A617" Size="110008" CompressionType="100" Encrypted="False" />
  <File Name="unit_oza_facade_interior_a_lod3.cgf" CRC32="0xADB54A00" Size="104" CompressionType="100" Encrypted="False" />
  <File Name="unit_oza_facade_interior_a_lod3.cgfm" CRC32="0x7B48CE88" Size="72776" CompressionType="100" Encrypted="False" />
  <File Name="unit_oza_facade_interior_a_lod4.cgf" CRC32="0x426CB8D5" Size="104" CompressionType="100" Encrypted="False" />
  <File Name="unit_oza_facade_interior_a_lod4.cgfm" CRC32="0xD8D4FA4B" Size="39040" CompressionType="100" Encrypted="False" />
  <File Name="unit_oza_facade_interior_a_lod5.cgf" CRC32="0x5680FAA1" Size="104" CompressionType="100" Encrypted="False" />
  <File Name="unit_oza_facade_interior_a_lod5.cgfm" CRC32="0xFBD78B6B" Size="13968" CompressionType="100" Encrypted="False" />
  <File Name="unit_oza_facade_interior_a.cgf" CRC32="0xB96CF938" Size="136328" CompressionType="100" Encrypted="False" />
  <File Name="unit_oza_facade_interior_a.cgfm" CRC32="0xDA2C821F" Size="450184" CompressionType="100" Encrypted="False" />
  <File Name="unit_oza_logo_a_lod1.cgf" CRC32="0x9F9C0C91" Size="104" CompressionType="100" Encrypted="False" />
  <File Name="unit_oza_logo_a_lod1.cgfm" CRC32="0xF7F6F61A" Size="16120" CompressionType="100" Encrypted="False" />
  <File Name="unit_oza_logo_a_lod2.cgf" CRC32="0x0558B533" Size="104" CompressionType="100" Encrypted="False" />
  <File Name="unit_oza_logo_a_lod2.cgfm" CRC32="0xFE62AA1E" Size="9208" CompressionType="100" Encrypted="False" />
  <File Name="unit_oza_logo_a_lod3.cgf" CRC32="0x55244569" Size="104" CompressionType="100" Encrypted="False" />
  <File Name="unit_oza_logo_a_lod3.cgfm" CRC32="0x3998A822" Size="6480" CompressionType="100" Encrypted="False" />
  <File Name="unit_oza_logo_a_lod4.cgf" CRC32="0x959DDF8B" Size="104" CompressionType="100" Encrypted="False" />
  <File Name="unit_oza_logo_a_lod4.cgfm" CRC32="0x1E96C6F1" Size="4624" CompressionType="100" Encrypted="False" />
  <File Name="unit_oza_logo_a_lod5.cgf" CRC32="0xF112E94D" Size="104" CompressionType="100" Encrypted="False" />
  <File Name="unit_oza_logo_a_lod5.cgfm" CRC32="0xFD94B7E4" Size="2416" CompressionType="100" Encrypted="False" />
  <File Name="unit_oza_logo_a.cgf" CRC32="0x053BBA47" Size="12968" CompressionType="100" Encrypted="False" />
  <File Name="unit_oza_logo_a.cgfm" CRC32="0x7BB5DCB4" Size="40936" CompressionType="100" Encrypted="False" />
  <File Name="unit_wallys_facade_interior_a_lod1.cgf" CRC32="0x42C9A089" Size="104" CompressionType="100" Encrypted="False" />
  <File Name="unit_wallys_facade_interior_a_lod1.cgfm" CRC32="0xC3312391" Size="505512" CompressionType="100" Encrypted="False" />
  <File Name="unit_wallys_facade_interior_a_lod2.cgf" CRC32="0x79E2AE5C" Size="104" CompressionType="100" Encrypted="False" />
  <File Name="unit_wallys_facade_interior_a_lod2.cgfm" CRC32="0x4D3A2CBF" Size="282456" CompressionType="100" Encrypted="False" />
  <File Name="unit_wallys_facade_interior_a_lod3.cgf" CRC32="0xDCF35AC9" Size="104" CompressionType="100" Encrypted="False" />
  <File Name="unit_wallys_facade_interior_a_lod3.cgfm" CRC32="0x86778036" Size="135416" CompressionType="100" Encrypted="False" />
  <File Name="unit_wallys_facade_interior_a_lod4.cgf" CRC32="0x422B5E4C" Size="104" CompressionType="100" Encrypted="False" />
  <File Name="unit_wallys_facade_interior_a_lod4.cgfm" CRC32="0x64EBB77D" Size="28272" CompressionType="100" Encrypted="False" />
  <File Name="unit_wallys_facade_interior_a.cgf" CRC32="0x7D7B1073" Size="526360" CompressionType="100" Encrypted="False" />
  <File Name="unit_wallys_facade_interior_a.cgfm" CRC32="0xAE514E54" Size="1562280" CompressionType="100" Encrypted="False" />
  <File Name="unit_wallys_facade_interior_b_lod1.cgf" CRC32="0x392557AB" Size="104" CompressionType="100" Encrypted="False" />
  <File Name="unit_wallys_facade_interior_b_lod1.cgfm" CRC32="0x4DFA461D" Size="141000" CompressionType="100" Encrypted="False" />
  <File Name="unit_wallys_facade_interior_b_lod2.cgf" CRC32="0xA37B8C8C" Size="104" CompressionType="100" Encrypted="False" />
  <File Name="unit_wallys_facade_interior_b_lod2.cgfm" CRC32="0xC6C36DAD" Size="67648" CompressionType="100" Encrypted="False" />
  <File Name="unit_wallys_facade_interior_b_lod3.cgf" CRC32="0x5467FC98" Size="104" CompressionType="100" Encrypted="False" />
  <File Name="unit_wallys_facade_interior_b_lod3.cgfm" CRC32="0xA7563FCD" Size="26112" CompressionType="100" Encrypted="False" />
  <File Name="unit_wallys_facade_interior_b_lod4.cgf" CRC32="0x882547E0" Size="104" CompressionType="100" Encrypted="False" />
  <File Name="unit_wallys_facade_interior_b_lod4.cgfm" CRC32="0x8C199D82" Size="8000" CompressionType="100" Encrypted="False" />
  <File Name="unit_wallys_facade_interior_b.cgf" CRC32="0x169BE66C" Size="111848" CompressionType="100" Encrypted="False" />
  <File Name="unit_wallys_facade_interior_b.cgfm" CRC32="0xDC24E656" Size="350696" CompressionType="100" Encrypted="False" />
  <File Name="unit_wallys_logo_a_lod1.cgf" CRC32="0xFE88938B" Size="104" CompressionType="100" Encrypted="False" />
  <File Name="unit_wallys_logo_a_lod1.cgfm" CRC32="0x4D9BB4BC" Size="15856" CompressionType="100" Encrypted="False" />
  <File Name="unit_wallys_logo_a_lod2.cgf" CRC32="0x9B86D638" Size="104" CompressionType="100" Encrypted="False" />
  <File Name="unit_wallys_logo_a_lod2.cgfm" CRC32="0x7455B2EE" Size="6912" CompressionType="100" Encrypted="False" />
  <File Name="unit_wallys_logo_a_lod3.cgf" CRC32="0x5D7B0451" Size="104" CompressionType="100" Encrypted="False" />
  <File Name="unit_wallys_logo_a_lod3.cgfm" CRC32="0x65CC3EFE" Size="3264" CompressionType="100" Encrypted="False" />
  <File Name="unit_wallys_logo_a.cgf" CRC32="0x0F17F7E1" Size="23432" CompressionType="100" Encrypted="False" />
  <File Name="unit_wallys_logo_a.cgfm" CRC32="0x063D35A4" Size="60464" CompressionType="100" Encrypted="False" />
  <File Name="unit_whammers_bar_neon_sign_a.cgf" CRC32="0x39A6D0BA" Size="34440" CompressionType="100" Encrypted="False" />
  <File Name="unit_whammers_bar_neon_sign_a.cgfm" CRC32="0xCAFA872C" Size="140600" CompressionType="100" Encrypted="False" />
  <File Name="unit_whammers_bar_underglow_a.cgf" CRC32="0xFB7435D0" Size="3728" CompressionType="100" Encrypted="False" />
  <File Name="unit_whammers_bar_underglow_a.cgfm" CRC32="0x98073082" Size="9856" CompressionType="100" Encrypted="False" />
  <File Name="unit_whammers_facade_exterior_b.cgf" CRC32="0x801CE530" Size="6272" CompressionType="100" Encrypted="False" />
  <File Name="unit_whammers_facade_exterior_b.cgfm" CRC32="0x7B941903" Size="14624" CompressionType="100" Encrypted="False" />
  <File Name="unit_whammers_facade_glass_001_a_lod1.cgf" CRC32="0x53CDE0D5" Size="104" CompressionType="100" Encrypted="False" />
  <File Name="unit_whammers_facade_glass_001_a_lod1.cgfm" CRC32="0x04AED0D2" Size="10728" CompressionType="100" Encrypted="False" />
  <File Name="unit_whammers_facade_glass_001_a_lod2.cgf" CRC32="0xE9CC3FE6" Size="104" CompressionType="100" Encrypted="False" />
  <File Name="unit_whammers_facade_glass_001_a_lod2.cgfm" CRC32="0x8FAD73CE" Size="5840" CompressionType="100" Encrypted="False" />
  <File Name="unit_whammers_facade_glass_001_a.cgf" CRC32="0xFDFBA1FD" Size="8696" CompressionType="100" Encrypted="False" />
  <File Name="unit_whammers_facade_glass_001_a.cgfm" CRC32="0xB0AB016F" Size="27176" CompressionType="100" Encrypted="False" />
  <File Name="unit_whammers_facade_glass_001_b_lod1.cgf" CRC32="0x255B01E7" Size="104" CompressionType="100" Encrypted="False" />
  <File Name="unit_whammers_facade_glass_001_b_lod1.cgfm" CRC32="0xFB25C916" Size="5128" CompressionType="100" Encrypted="False" />
  <File Name="unit_whammers_facade_glass_001_b_lod2.cgf" CRC32="0xEA9E512A" Size="104" CompressionType="100" Encrypted="False" />
  <File Name="unit_whammers_facade_glass_001_b_lod2.cgfm" CRC32="0x3D529795" Size="3336" CompressionType="100" Encrypted="False" />
  <File Name="unit_whammers_facade_glass_001_b.cgf" CRC32="0x7A9BF7D9" Size="5584" CompressionType="100" Encrypted="False" />
  <File Name="unit_whammers_facade_glass_001_b.cgfm" CRC32="0xC763DB58" Size="16496" CompressionType="100" Encrypted="False" />
  <File Name="unit_whammers_facade_glass_001_c_lod1.cgf" CRC32="0x6D4CDEAC" Size="104" CompressionType="100" Encrypted="False" />
  <File Name="unit_whammers_facade_glass_001_c_lod1.cgfm" CRC32="0x6F86EAC1" Size="4816" CompressionType="100" Encrypted="False" />
  <File Name="unit_whammers_facade_glass_001_c_lod2.cgf" CRC32="0x638944CB" Size="104" CompressionType="100" Encrypted="False" />
  <File Name="unit_whammers_facade_glass_001_c_lod2.cgfm" CRC32="0xB794095B" Size="3440" CompressionType="100" Encrypted="False" />
  <File Name="unit_whammers_facade_glass_001_c.cgf" CRC32="0x8FB26659" Size="5584" CompressionType="100" Encrypted="False" />
  <File Name="unit_whammers_facade_glass_001_c.cgfm" CRC32="0x0E697F6E" Size="13968" CompressionType="100" Encrypted="False" />
  <File Name="unit_whammers_facade_glass_001_d_lod1.cgf" CRC32="0xCAB18006" Size="104" CompressionType="100" Encrypted="False" />
  <File Name="unit_whammers_facade_glass_001_d_lod1.cgfm" CRC32="0x6394B4EF" Size="8912" CompressionType="100" Encrypted="False" />
  <File Name="unit_whammers_facade_glass_001_d_lod2.cgf" CRC32="0xBB84A449" Size="104" CompressionType="100" Encrypted="False" />
  <File Name="unit_whammers_facade_glass_001_d_lod2.cgfm" CRC32="0xD19B09A4" Size="5584" CompressionType="100" Encrypted="False" />
  <File Name="unit_whammers_facade_glass_001_d.cgf" CRC32="0x83B5F7DC" Size="8680" CompressionType="100" Encrypted="False" />
  <File Name="unit_whammers_facade_glass_001_d.cgfm" CRC32="0xE62F2D34" Size="26288" CompressionType="100" Encrypted="False" />
  <File Name="unit_whammers_facade_interior_a_lod1.cgf" CRC32="0xE67AAB0A" Size="104" CompressionType="100" Encrypted="False" />
  <File Name="unit_whammers_facade_interior_a_lod1.cgfm" CRC32="0x3B38D3E5" Size="124584" CompressionType="100" Encrypted="False" />
  <File Name="unit_whammers_facade_interior_a_lod2.cgf" CRC32="0xCD503C52" Size="104" CompressionType="100" Encrypted="False" />
  <File Name="unit_whammers_facade_interior_a_lod2.cgfm" CRC32="0x0AEA0471" Size="66432" CompressionType="100" Encrypted="False" />
  <File Name="unit_whammers_facade_interior_a_lod3.cgf" CRC32="0xDB050E1A" Size="104" CompressionType="100" Encrypted="False" />
  <File Name="unit_whammers_facade_interior_a_lod3.cgfm" CRC32="0x9B56264F" Size="36608" CompressionType="100" Encrypted="False" />
  <File Name="unit_whammers_facade_interior_a_lod4.cgf" CRC32="0xE245C53A" Size="104" CompressionType="100" Encrypted="False" />
  <File Name="unit_whammers_facade_interior_a_lod4.cgfm" CRC32="0xB3CE0BDE" Size="20800" CompressionType="100" Encrypted="False" />
  <File Name="unit_whammers_facade_interior_a_lod5.cgf" CRC32="0xFC692E50" Size="104" CompressionType="100" Encrypted="False" />
  <File Name="unit_whammers_facade_interior_a_lod5.cgfm" CRC32="0x8C78B07D" Size="13912" CompressionType="100" Encrypted="False" />
  <File Name="unit_whammers_facade_interior_a.cgf" CRC32="0x70EE66BC" Size="153648" CompressionType="100" Encrypted="False" />
  <File Name="unit_whammers_facade_interior_a.cgfm" CRC32="0xB9FAF649" Size="446944" CompressionType="100" Encrypted="False" />
  <File Name="unit_whammers_facade_interior_b_lod1.cgf" CRC32="0x12B7F19B" Size="104" CompressionType="100" Encrypted="False" />
  <File Name="unit_whammers_facade_interior_b_lod1.cgfm" CRC32="0xDD787A77" Size="149776" CompressionType="100" Encrypted="False" />
  <File Name="unit_whammers_facade_interior_b_lod2.cgf" CRC32="0x185D4612" Size="104" CompressionType="100" Encrypted="False" />
  <File Name="unit_whammers_facade_interior_b_lod2.cgfm" CRC32="0x76643329" Size="77496" CompressionType="100" Encrypted="False" />
  <File Name="unit_whammers_facade_interior_b_lod3.cgf" CRC32="0x9E85248D" Size="104" CompressionType="100" Encrypted="False" />
  <File Name="unit_whammers_facade_interior_b_lod3.cgfm" CRC32="0x6D302167" Size="45024" CompressionType="100" Encrypted="False" />
  <File Name="unit_whammers_facade_interior_b_lod4.cgf" CRC32="0x5E846C30" Size="104" CompressionType="100" Encrypted="False" />
  <File Name="unit_whammers_facade_interior_b_lod4.cgfm" CRC32="0x895A7C11" Size="22488" CompressionType="100" Encrypted="False" />
  <File Name="unit_whammers_facade_interior_b_lod5.cgf" CRC32="0xB95A86E8" Size="104" CompressionType="100" Encrypted="False" />
  <File Name="unit_whammers_facade_interior_b_lod5.cgfm" CRC32="0x2D44CEE4" Size="9632" CompressionType="100" Encrypted="False" />
  <File Name="unit_whammers_facade_interior_b.cgf" CRC32="0x4D1F4292" Size="132640" CompressionType="100" Encrypted="False" />
  <File Name="unit_whammers_facade_interior_b.cgfm" CRC32="0x6AE7FE87" Size="380856" CompressionType="100" Encrypted="False" />
</Directory>