<?xml version="1.0" encoding="utf-8"?>
<Struct Name="ServiceBeaconGlobalParams">
  <Property Name="quantumTravelPointClass" Type="EntityClassDefinition" />
  <Property Name="missionTypeRecord" Type="MissionType" />
  <Property Name="personalTransportDetectedNotification" Type="ServiceBeaconNotificationParams" />
  <Property Name="combatAssistanceDetectedNotification" Type="ServiceBeaconNotificationParams" />
  <Property Name="escortDetectedNotification" Type="ServiceBeaconNotificationParams" />
  <Property Name="refuelDetectedNotification" Type="ServiceBeaconNotificationParams" />
  <Property Name="reviveDetectedNotification" Type="ServiceBeaconNotificationParams" />
  <Property Name="healDetectedNotification" Type="ServiceBeaconNotificationParams" />
  <Property Name="contractAcceptedNotification" Type="ServiceBeaconNotificationParams" />
  <Property Name="contractCancelledNotification" Type="ServiceBeaconNotificationParams" />
  <Property Name="contractNoLongerAvailableNotification" Type="ServiceBeaconNotificationParams" />
  <Property Name="contractCompletedInitiatorNotification" Type="ServiceBeaconNotificationParams" />
  <Property Name="contractCompletedProviderNotification" Type="ServiceBeaconNotificationParams" />
  <Property Name="providerWithinRangeNotification" Type="ServiceBeaconNotificationParams" />
  <Property Name="spoofedContractOfferedNotification" Type="ServiceBeaconNotificationParams" />
  <Property Name="contractProviderName" Type="string" />
  <Property Name="vehicleLocationChosenForPersonalTransport" Type="string" />
  <Property Name="providerNameToken" Type="string" />
  <Property Name="initiatorNameToken" Type="string" />
  <Property Name="selectedDestinationToken" Type="string" />
  <Property Name="contractTypeToken" Type="string" />
  <Property Name="distanceToInitiatorToken" Type="string" />
  <Property Name="initiatorLocationToken" Type="string" />
  <Property Name="paymentAmountToken" Type="string" />
  <Property Name="openSpaceLocationName" Type="string" />
  <Property Name="allReputationsLabel" Type="string" />
  <Property Name="oneStarReputationLabel" Type="string" />
  <Property Name="twoStarReputationLabel" Type="string" />
  <Property Name="threeStarReputationLabel" Type="string" />
  <Property Name="fourStarReputationLabel" Type="string" />
  <Property Name="fiveStarReputationLabel" Type="string" />
  <Property Name="invalidTypeErrorMessage" Type="string" />
  <Property Name="invalidReputationErrorMessage" Type="string" />
  <Property Name="priceIsZeroErrorMessage" Type="string" />
  <Property Name="insufficientFundsErrorMessage" Type="string" />
  <Property Name="invalidLocationSelectedErrorMessage" Type="string" />
</Struct>