<?xml version="1.0" encoding="utf-16"?>
<Subsumption>
  <Subactivity ID="05563351-7ae3-463c-b9d8-181d17bb1395" Name="InspectClose" Renamable="False" Deletable="False" ReadOnly="False" Static="False" AutoGenerated="False" SiblingLinkage="False" Priority="0" Resumable="False" FunctionType="UseChannelFunction" PossibleFunctionID="00000000-0000-0000-0000-000000000000" RelativeProbabilityFunctionID="00000000-0000-0000-0000-000000000000" DefaultWidth="0" Cooldown="0" GridSize="35">
    <DisplayGridSize Width="4000" Height="4000" />
    <Variables>
      <Variable ID="cab7e049-25fe-4d21-a31b-ddb8c0a42838" Index="0" Name="AdditionalTags" Renamable="True" Deletable="True" ReadOnly="False" Static="False" AutoGenerated="False" SiblingLinkage="False" Type="MannequinTags" VariableTypeID="255218ba-8c03-471d-98b4-d64dfacc0946" StorageType="Normal" DataSource="Subsumption" Overloadable="False" Exportable="False" LoadOnce="False" Shared="False" Hint="empty" DependsUpon="00000000-0000-0000-0000-000000000000" Persists="False" UpdateMethod="Manual" ParameterType="None" EventParameter="False" Attribute="False" AllowExplicitValues="True" AllowEditing="True" AllowNull="True" AccessModifier="Private" MinValue="0" MaxValue="1" ValueChangePerSecond="0.001" />
      <Variable ID="bb67a83a-d771-4956-b6cb-4f64029a8727" Index="1" Name="This" Renamable="False" Deletable="False" ReadOnly="True" Static="False" AutoGenerated="False" SiblingLinkage="False" Type="NPC" VariableTypeID="21b2be94-333c-4234-afa3-9d8723b5b73c" StorageType="Normal" DataSource="Subsumption" Overloadable="False" Exportable="False" LoadOnce="False" Shared="False" Hint="empty" DependsUpon="00000000-0000-0000-0000-000000000000" Persists="False" UpdateMethod="Manual" ParameterType="None" EventParameter="False" Attribute="False" AllowExplicitValues="True" AllowEditing="True" AllowNull="True" AccessModifier="Private" MinValue="0" MaxValue="1" ValueChangePerSecond="0.001" />
      <Variable ID="67885af7-2a07-495d-a07a-03c916e9eab9" Index="2" Name="Usable" Renamable="False" Deletable="False" ReadOnly="True" Static="False" AutoGenerated="False" SiblingLinkage="False" Type="Usable" VariableTypeID="87918994-d49e-4456-b9b7-2f9437e58bfa" StorageType="Normal" DataSource="Subsumption" Overloadable="False" Exportable="False" LoadOnce="False" Shared="False" Hint="empty" DependsUpon="00000000-0000-0000-0000-000000000000" Persists="False" UpdateMethod="Manual" ParameterType="None" EventParameter="False" Attribute="False" AllowExplicitValues="True" AllowEditing="True" AllowNull="True" AccessModifier="Private" MinValue="0" MaxValue="1" ValueChangePerSecond="0.001" />
    </Variables>
    <TermManager Expression="empty" SearchMode="RangeOnly" SearchDistance="40">
      <Terms />
    </TermManager>
    <RequiredEvents />
    <SecondarySubactivityPermissions />
    <Comments />
    <Tasks>
      <Task ID="08eb61ae-c0a9-400b-824f-ac38929d807f" Index="0" Name="Task_001" Renamable="True" Deletable="True" ReadOnly="False" Static="False" AutoGenerated="False" SiblingLinkage="False" Archetype="e005de61-7d6e-460f-b963-109bac1a4b56" CustomWidth="0" ThreadParentVariable="00000000-0000-0000-0000-000000000000">
        <Position X="524" Y="44" />
        <Links Success="63e90c19-960e-4fd9-84dc-56eb02e4963b" />
      </Task>
      <Task ID="63e90c19-960e-4fd9-84dc-56eb02e4963b" Index="1" Name="Task_003" Renamable="True" Deletable="True" ReadOnly="False" Static="False" AutoGenerated="False" SiblingLinkage="False" Archetype="ddf50dea-a339-498f-bd4b-b36dbe286726" CustomWidth="0" ThreadParentVariable="00000000-0000-0000-0000-000000000000">
        <Position X="394" Y="214" />
        <Links Success="f2f32d80-f30f-4362-afe0-7c13bce7374a" Failure="985e141d-2c13-4618-a5b3-b67b7514496a" />
        <Variables>
          <Variable ID="6a6804fd-c178-4413-abb0-94b802e47715" Value="67885af7-2a07-495d-a07a-03c916e9eab9" VariableName="Usable" />
          <Variable ID="79079dea-b4f5-497a-b9fc-1abf942a9064" Value="85b16e4d-ae13-49e6-9328-bac2a804ce33" VariableName="Usable - Cupboard::Close">
            <Variables />
          </Variable>
        </Variables>
      </Task>
      <Task ID="f2f32d80-f30f-4362-afe0-7c13bce7374a" Index="2" Name="Task_004" Renamable="True" Deletable="True" ReadOnly="False" Static="False" AutoGenerated="False" SiblingLinkage="False" Archetype="bcc553a7-61e9-4e23-97e7-32a7a3928497" CustomWidth="0" ThreadParentVariable="00000000-0000-0000-0000-000000000000" DebugFailure="Failed animate task to open the Crate">
        <Position X="294" Y="504" />
        <Links Failure="985e141d-2c13-4618-a5b3-b67b7514496a" />
        <Variables>
          <Variable ID="8276073d-0c93-45f2-8198-0d1a96be6400" Value="usable_action" Type="Explicit" />
          <Variable ID="cf00c6d4-e302-4419-a808-4e5b6928ad4a" Value="inspectclose" Type="Explicit" />
          <Variable ID="ae21a524-0577-4c26-a62a-e2af168f1d67" Value="cab7e049-25fe-4d21-a31b-ddb8c0a42838" VariableName="AdditionalTags" />
        </Variables>
      </Task>
      <Task ID="985e141d-2c13-4618-a5b3-b67b7514496a" Index="3" Name="Task_006" Renamable="True" Deletable="True" ReadOnly="False" Static="False" AutoGenerated="False" SiblingLinkage="False" Archetype="f4e0d1a8-246a-4bb1-b7ba-ab948934867e" CustomWidth="0" ThreadParentVariable="00000000-0000-0000-0000-000000000000" DebugStart="Fail to close">
        <Position X="604" Y="774" />
        <Links />
      </Task>
    </Tasks>
  </Subactivity>
</Subsumption>