<?xml version="1.0" encoding="utf-16"?>
<Entities sorted="1">
  <Entity Name="Dust_Motes_ALL.dust_motes_4m3_loop_1-005" Radius="0" Pos="5.0228669999999997,-2.7919529999999999,-3.1560290000000002" Rotate="0.70710677,0.70710677,0,0" EntityClass="ParticleEffect" EntityClassGUID="8bb2877c-25d7-4832-97e1-e603ff8eba4b" EntityCryGUID="40f58b6c-6e12-c246-003b-943b6260ecb0" CastShadowMinSpec="1">
    <PropertiesDataCore>
      <EntityComponentParticleEffect __type="ParticleEffectParams" comment="empty" activate="1" spawnProbability="1.0" primed="0" countPerUnit="0" attachType="None" attachForm="Vertices" registerByBbox="0" clipToVisArea="Local" gpuVisAreaCullingMode="Default" forceDisableShadows="0" tesselationAmount="Default" attachToZone="Parent" seed="-1" renderLayer="Default">
        <particleEffect __type="GlobalResourceParticle" path="b8bd8914-4e9c-e661-dcb9-e8284f06ef3a|environments/generic/generic_dust_fx.Dust_Motes_ALL.dust_motes_4m3_loop_1" />
        <scale __fullyInstanced="1" __baseType="CustomFloat" __type="FixedFloat" value="0.7" />
        <emissionSizeScale __type="Vec3" x="1.0" y="1.0" z="1.0" />
        <speedScale __fullyInstanced="1" __baseType="CustomFloat" __type="FixedFloat" value="1.0" />
        <timeScale __fullyInstanced="1" __baseType="CustomFloat" __type="FixedFloat" value="1.0" />
        <countScale __fullyInstanced="1" __baseType="CustomFloat" __type="RandomFloat" minimum="0.1" maximum="0.3" />
        <strength __fullyInstanced="1" __baseType="CustomFloat" __type="FixedFloat" value="-1.0" />
        <alphaScale __fullyInstanced="1" __baseType="CustomFloat" __type="FixedFloat" value="1.0" />
        <pulsePeriod __fullyInstanced="1" __baseType="CustomFloat" __type="FixedFloat" value="0.0" />
        <externalTint __fullyInstanced="1" __baseType="ParticleEffectNoneTintingParams" __type="ParticleEffectNoneTintingParams" />
        <audio __type="ParticleEffectAudioParams" enableAudio="1" isManagedAudioObject="0" attenuationScale="1.0" volume="0.0">
          <audioRTPC __type="AudioRtpc" rtpc="particlefx" />
        </audio>
        <gpuAudio __type="GPUParticleAudioStruct">
          <emissionStartTriggerOneShot __type="GlobalResourceAudio" audioTrigger="empty" />
          <emissionStopTriggerOneShot __type="GlobalResourceAudio" audioTrigger="empty" />
          <emissionStartTriggerLoop __type="GlobalResourceAudio" audioTrigger="empty" />
          <emissionStopTriggerLoop __type="GlobalResourceAudio" audioTrigger="empty" />
          <pulseDurationRtpc __type="AudioRtpc" rtpc="Particle_Pulse_Duration" />
          <normPulseTimeRtpc __type="AudioRtpc" rtpc="Particle_Normalized_Pulse_Time" />
          <strengthValRtpc __type="AudioRtpc" rtpc="Particle_Strength" />
          <scalingFactorRtpc __type="AudioRtpc" rtpc="Particle_ScalingFactor" />
        </gpuAudio>
      </EntityComponentParticleEffect>
    </PropertiesDataCore>
    <Tags>
      <Tag TagId="226a978c-41d0-407e-9137-7902df0c2ab2" />
    </Tags>
    <RenderProxy AllowBakedRendering="1" />
  </Entity>
  <Entity Name="Steam_JET.steam_jet_2x16m_loop_2_gpu-001" Radius="0" Pos="3.6829770000000002,-4.1043180000000001,-3.2600519999999999" Rotate="0.60500687,0.62543988,0.36351195,-0.33264193" EntityClass="ParticleEffect" EntityClassGUID="8bb2877c-25d7-4832-97e1-e603ff8eba4b" EntityCryGUID="48e0e995-4605-9503-5187-7f7a40b1c8bb" CastShadowMinSpec="1">
    <PropertiesDataCore>
      <EntityComponentParticleEffect __type="ParticleEffectParams" comment="empty" activate="1" spawnProbability="0.750903" primed="0" countPerUnit="0" attachType="None" attachForm="Vertices" registerByBbox="0" clipToVisArea="None" gpuVisAreaCullingMode="Default" forceDisableShadows="0" tesselationAmount="Default" attachToZone="Parent" seed="-1" renderLayer="Default">
        <particleEffect __type="GlobalResourceParticle" path="86e33715-32d4-1f59-1212-83adde1f4535|damage/lt_damage/lt_smoke_fx.LT_Smoke_Int.lt_smoke_int_1m_loop_constant_gpu_decoupled" />
        <scale __fullyInstanced="1" __baseType="CustomFloat" __type="FixedFloat" value="1.0" />
        <emissionSizeScale __type="Vec3" x="1.0" y="1.0" z="1.0" />
        <speedScale __fullyInstanced="1" __baseType="CustomFloat" __type="FixedFloat" value="1.0" />
        <timeScale __fullyInstanced="1" __baseType="CustomFloat" __type="FixedFloat" value="1.0" />
        <countScale __fullyInstanced="1" __baseType="CustomFloat" __type="FixedFloat" value="1.0" />
        <strength __fullyInstanced="1" __baseType="CustomFloat" __type="FixedFloat" value="-1.0" />
        <alphaScale __fullyInstanced="1" __baseType="CustomFloat" __type="FixedFloat" value="1.0" />
        <pulsePeriod __fullyInstanced="1" __baseType="CustomFloat" __type="FixedFloat" value="0.0" />
        <externalTint __fullyInstanced="1" __baseType="ParticleEffectNoneTintingParams" __type="ParticleEffectNoneTintingParams" />
        <audio __type="ParticleEffectAudioParams" enableAudio="1" isManagedAudioObject="0" attenuationScale="1.0" volume="0.0">
          <audioRTPC __type="AudioRtpc" rtpc="particlefx" />
        </audio>
        <gpuAudio __type="GPUParticleAudioStruct">
          <emissionStartTriggerOneShot __type="GlobalResourceAudio" audioTrigger="empty" />
          <emissionStopTriggerOneShot __type="GlobalResourceAudio" audioTrigger="empty" />
          <emissionStartTriggerLoop __type="GlobalResourceAudio" audioTrigger="empty" />
          <emissionStopTriggerLoop __type="GlobalResourceAudio" audioTrigger="empty" />
          <pulseDurationRtpc __type="AudioRtpc" rtpc="Particle_Pulse_Duration" />
          <normPulseTimeRtpc __type="AudioRtpc" rtpc="Particle_Normalized_Pulse_Time" />
          <strengthValRtpc __type="AudioRtpc" rtpc="Particle_Strength" />
          <scalingFactorRtpc __type="AudioRtpc" rtpc="Particle_ScalingFactor" />
        </gpuAudio>
      </EntityComponentParticleEffect>
    </PropertiesDataCore>
    <Tags>
      <Tag TagId="226a978c-41d0-407e-9137-7902df0c2ab2" />
    </Tags>
    <RenderProxy AllowBakedRendering="1" />
  </Entity>
  <Entity Name="Steam_LINGER.steam_linger_2x1m_loop_1_gpu-008" Radius="0" Pos="-4.6775609999999999,-5.3343499999999997,-1.4460090000000001" Rotate="-0.5,0.5,0.5,-0.5" EntityClass="ParticleEffect" EntityClassGUID="8bb2877c-25d7-4832-97e1-e603ff8eba4b" EntityCryGUID="4f8af36d-ba9a-7453-ba74-cc11d88c71a4" CastShadowMinSpec="1">
    <PropertiesDataCore>
      <EntityComponentParticleEffect __type="ParticleEffectParams" comment="empty" activate="1" spawnProbability="0.884477" primed="0" countPerUnit="0" attachType="None" attachForm="Vertices" registerByBbox="0" clipToVisArea="None" gpuVisAreaCullingMode="Default" forceDisableShadows="0" tesselationAmount="Default" attachToZone="Parent" seed="-1" renderLayer="Default">
        <particleEffect __type="GlobalResourceParticle" path="1df31750-d0f6-b35e-e40c-a1fdba7f8e4e|environments/generic/generic_steam_fx.Steam_RISE.steam_rise_2x1m_loop_1_gpu" />
        <scale __fullyInstanced="1" __baseType="CustomFloat" __type="FixedFloat" value="0.4" />
        <emissionSizeScale __type="Vec3" x="1.0" y="1.0" z="1.0" />
        <speedScale __fullyInstanced="1" __baseType="CustomFloat" __type="FixedFloat" value="1.0" />
        <timeScale __fullyInstanced="1" __baseType="CustomFloat" __type="RandomFloat" minimum="1.0" maximum="1.2" />
        <countScale __fullyInstanced="1" __baseType="CustomFloat" __type="FixedFloat" value="1.0" />
        <strength __fullyInstanced="1" __baseType="CustomFloat" __type="FixedFloat" value="-1.0" />
        <alphaScale __fullyInstanced="1" __baseType="CustomFloat" __type="FixedFloat" value="1.0" />
        <pulsePeriod __fullyInstanced="1" __baseType="CustomFloat" __type="FixedFloat" value="0.0" />
        <externalTint __fullyInstanced="1" __baseType="ParticleEffectNoneTintingParams" __type="ParticleEffectNoneTintingParams" />
        <audio __type="ParticleEffectAudioParams" enableAudio="1" isManagedAudioObject="0" attenuationScale="1.0" volume="0.0">
          <audioRTPC __type="AudioRtpc" rtpc="particlefx" />
        </audio>
        <gpuAudio __type="GPUParticleAudioStruct">
          <emissionStartTriggerOneShot __type="GlobalResourceAudio" audioTrigger="empty" />
          <emissionStopTriggerOneShot __type="GlobalResourceAudio" audioTrigger="empty" />
          <emissionStartTriggerLoop __type="GlobalResourceAudio" audioTrigger="empty" />
          <emissionStopTriggerLoop __type="GlobalResourceAudio" audioTrigger="empty" />
          <pulseDurationRtpc __type="AudioRtpc" rtpc="Particle_Pulse_Duration" />
          <normPulseTimeRtpc __type="AudioRtpc" rtpc="Particle_Normalized_Pulse_Time" />
          <strengthValRtpc __type="AudioRtpc" rtpc="Particle_Strength" />
          <scalingFactorRtpc __type="AudioRtpc" rtpc="Particle_ScalingFactor" />
        </gpuAudio>
      </EntityComponentParticleEffect>
    </PropertiesDataCore>
    <Tags>
      <Tag TagId="226a978c-41d0-407e-9137-7902df0c2ab2" />
    </Tags>
    <RenderProxy AllowBakedRendering="1" />
  </Entity>
  <Entity Name="Dust_Motes_ALL.dust_motes_8x12x20m_loop_1-006" Radius="0" Pos="8.0425170000000001,-1.9576499999999999,-2.6959430000000002" Rotate="0,0,0.70710677,0.70710677" EntityClass="ParticleEffect" EntityClassGUID="8bb2877c-25d7-4832-97e1-e603ff8eba4b" EntityCryGUID="4112baf1-ef38-2399-05aa-f6f0169b6bbf" CastShadowMinSpec="1">
    <PropertiesDataCore>
      <EntityComponentParticleEffect __type="ParticleEffectParams" comment="empty" activate="1" spawnProbability="1.0" primed="0" countPerUnit="0" attachType="None" attachForm="Vertices" registerByBbox="0" clipToVisArea="None" gpuVisAreaCullingMode="Default" forceDisableShadows="0" tesselationAmount="Default" attachToZone="Parent" seed="-1" renderLayer="Default">
        <particleEffect __type="GlobalResourceParticle" path="df19eb38-2ad9-4578-8140-bf664d3a1401|environments/generic/generic_dust_fx.Dust_Motes_ALL.dust_motes_4x8x12m_loop_1" />
        <scale __fullyInstanced="1" __baseType="CustomFloat" __type="FixedFloat" value="0.35" />
        <emissionSizeScale __type="Vec3" x="1.0" y="1.0" z="1.0" />
        <speedScale __fullyInstanced="1" __baseType="CustomFloat" __type="FixedFloat" value="1.0" />
        <timeScale __fullyInstanced="1" __baseType="CustomFloat" __type="FixedFloat" value="1.0" />
        <countScale __fullyInstanced="1" __baseType="CustomFloat" __type="FixedFloat" value="1.0" />
        <strength __fullyInstanced="1" __baseType="CustomFloat" __type="FixedFloat" value="-1.0" />
        <alphaScale __fullyInstanced="1" __baseType="CustomFloat" __type="FixedFloat" value="1.0" />
        <pulsePeriod __fullyInstanced="1" __baseType="CustomFloat" __type="FixedFloat" value="0.0" />
        <externalTint __fullyInstanced="1" __baseType="ParticleEffectNoneTintingParams" __type="ParticleEffectNoneTintingParams" />
        <audio __type="ParticleEffectAudioParams" enableAudio="1" isManagedAudioObject="0" attenuationScale="1.0" volume="0.0">
          <audioRTPC __type="AudioRtpc" rtpc="particlefx" />
        </audio>
        <gpuAudio __type="GPUParticleAudioStruct">
          <emissionStartTriggerOneShot __type="GlobalResourceAudio" audioTrigger="empty" />
          <emissionStopTriggerOneShot __type="GlobalResourceAudio" audioTrigger="empty" />
          <emissionStartTriggerLoop __type="GlobalResourceAudio" audioTrigger="empty" />
          <emissionStopTriggerLoop __type="GlobalResourceAudio" audioTrigger="empty" />
          <pulseDurationRtpc __type="AudioRtpc" rtpc="Particle_Pulse_Duration" />
          <normPulseTimeRtpc __type="AudioRtpc" rtpc="Particle_Normalized_Pulse_Time" />
          <strengthValRtpc __type="AudioRtpc" rtpc="Particle_Strength" />
          <scalingFactorRtpc __type="AudioRtpc" rtpc="Particle_ScalingFactor" />
        </gpuAudio>
      </EntityComponentParticleEffect>
    </PropertiesDataCore>
    <Tags>
      <Tag TagId="226a978c-41d0-407e-9137-7902df0c2ab2" />
    </Tags>
    <RenderProxy AllowBakedRendering="1" />
  </Entity>
  <Entity Name="Dust_Motes_ALL.dust_motes_8x12x20m_loop_1-007" Radius="0" Pos="-8.1890859999999996,-1.9576499999999999,-2.6959430000000002" Rotate="0,0,0.70710677,0.70710677" EntityClass="ParticleEffect" EntityClassGUID="8bb2877c-25d7-4832-97e1-e603ff8eba4b" EntityCryGUID="4d539ad2-62cf-4fab-87f7-c185ede29191" CastShadowMinSpec="1">
    <PropertiesDataCore>
      <EntityComponentParticleEffect __type="ParticleEffectParams" comment="empty" activate="1" spawnProbability="1.0" primed="0" countPerUnit="0" attachType="None" attachForm="Vertices" registerByBbox="0" clipToVisArea="None" gpuVisAreaCullingMode="Default" forceDisableShadows="0" tesselationAmount="Default" attachToZone="Parent" seed="-1" renderLayer="Default">
        <particleEffect __type="GlobalResourceParticle" path="df19eb38-2ad9-4578-8140-bf664d3a1401|environments/generic/generic_dust_fx.Dust_Motes_ALL.dust_motes_4x8x12m_loop_1" />
        <scale __fullyInstanced="1" __baseType="CustomFloat" __type="FixedFloat" value="0.35" />
        <emissionSizeScale __type="Vec3" x="1.0" y="1.0" z="1.0" />
        <speedScale __fullyInstanced="1" __baseType="CustomFloat" __type="FixedFloat" value="1.0" />
        <timeScale __fullyInstanced="1" __baseType="CustomFloat" __type="FixedFloat" value="1.0" />
        <countScale __fullyInstanced="1" __baseType="CustomFloat" __type="FixedFloat" value="1.0" />
        <strength __fullyInstanced="1" __baseType="CustomFloat" __type="FixedFloat" value="-1.0" />
        <alphaScale __fullyInstanced="1" __baseType="CustomFloat" __type="FixedFloat" value="1.0" />
        <pulsePeriod __fullyInstanced="1" __baseType="CustomFloat" __type="FixedFloat" value="0.0" />
        <externalTint __fullyInstanced="1" __baseType="ParticleEffectNoneTintingParams" __type="ParticleEffectNoneTintingParams" />
        <audio __type="ParticleEffectAudioParams" enableAudio="1" isManagedAudioObject="0" attenuationScale="1.0" volume="0.0">
          <audioRTPC __type="AudioRtpc" rtpc="particlefx" />
        </audio>
        <gpuAudio __type="GPUParticleAudioStruct">
          <emissionStartTriggerOneShot __type="GlobalResourceAudio" audioTrigger="empty" />
          <emissionStopTriggerOneShot __type="GlobalResourceAudio" audioTrigger="empty" />
          <emissionStartTriggerLoop __type="GlobalResourceAudio" audioTrigger="empty" />
          <emissionStopTriggerLoop __type="GlobalResourceAudio" audioTrigger="empty" />
          <pulseDurationRtpc __type="AudioRtpc" rtpc="Particle_Pulse_Duration" />
          <normPulseTimeRtpc __type="AudioRtpc" rtpc="Particle_Normalized_Pulse_Time" />
          <strengthValRtpc __type="AudioRtpc" rtpc="Particle_Strength" />
          <scalingFactorRtpc __type="AudioRtpc" rtpc="Particle_ScalingFactor" />
        </gpuAudio>
      </EntityComponentParticleEffect>
    </PropertiesDataCore>
    <Tags>
      <Tag TagId="226a978c-41d0-407e-9137-7902df0c2ab2" />
    </Tags>
    <RenderProxy AllowBakedRendering="1" />
  </Entity>
  <Entity Name="Steam_JET.steam_jet_1x2m_loop_1_gpu_decoupled-001" Radius="0" Pos="-7.8460900000000002,-0.61095500000000003,-2.0359080000000001" Rotate="0.28195819,0.28195819,-0.64845937,0.64845937" EntityClass="ParticleEffect" EntityClassGUID="8bb2877c-25d7-4832-97e1-e603ff8eba4b" EntityCryGUID="439fef6f-982e-0c7d-4efa-880312cd7ab1" CastShadowMinSpec="1">
    <PropertiesDataCore>
      <EntityComponentParticleEffect __type="ParticleEffectParams" comment="empty" activate="1" spawnProbability="0.722022" primed="0" countPerUnit="0" attachType="None" attachForm="Vertices" registerByBbox="0" clipToVisArea="None" gpuVisAreaCullingMode="Default" forceDisableShadows="0" tesselationAmount="Default" attachToZone="Parent" seed="-1" renderLayer="Default">
        <particleEffect __type="GlobalResourceParticle" path="0a4cbde4-ff67-ee38-4c0f-4a60735fa578|environments/generic/generic_steam_fx.Steam_JET.steam_jet_2x2m_loop_2_gpu" />
        <scale __fullyInstanced="1" __baseType="CustomFloat" __type="FixedFloat" value="1.0" />
        <emissionSizeScale __type="Vec3" x="1.0" y="1.0" z="1.0" />
        <speedScale __fullyInstanced="1" __baseType="CustomFloat" __type="FixedFloat" value="1.0" />
        <timeScale __fullyInstanced="1" __baseType="CustomFloat" __type="RandomFloat" minimum="1.5" maximum="2.0" />
        <countScale __fullyInstanced="1" __baseType="CustomFloat" __type="FixedFloat" value="1.0" />
        <strength __fullyInstanced="1" __baseType="CustomFloat" __type="FixedFloat" value="-1.0" />
        <alphaScale __fullyInstanced="1" __baseType="CustomFloat" __type="FixedFloat" value="1.0" />
        <pulsePeriod __fullyInstanced="1" __baseType="CustomFloat" __type="FixedFloat" value="0.0" />
        <externalTint __fullyInstanced="1" __baseType="ParticleEffectNoneTintingParams" __type="ParticleEffectNoneTintingParams" />
        <audio __type="ParticleEffectAudioParams" enableAudio="1" isManagedAudioObject="0" attenuationScale="1.0" volume="0.0">
          <audioRTPC __type="AudioRtpc" rtpc="particlefx" />
        </audio>
        <gpuAudio __type="GPUParticleAudioStruct">
          <emissionStartTriggerOneShot __type="GlobalResourceAudio" audioTrigger="empty" />
          <emissionStopTriggerOneShot __type="GlobalResourceAudio" audioTrigger="empty" />
          <emissionStartTriggerLoop __type="GlobalResourceAudio" audioTrigger="empty" />
          <emissionStopTriggerLoop __type="GlobalResourceAudio" audioTrigger="empty" />
          <pulseDurationRtpc __type="AudioRtpc" rtpc="Particle_Pulse_Duration" />
          <normPulseTimeRtpc __type="AudioRtpc" rtpc="Particle_Normalized_Pulse_Time" />
          <strengthValRtpc __type="AudioRtpc" rtpc="Particle_Strength" />
          <scalingFactorRtpc __type="AudioRtpc" rtpc="Particle_ScalingFactor" />
        </gpuAudio>
      </EntityComponentParticleEffect>
    </PropertiesDataCore>
    <Tags>
      <Tag TagId="226a978c-41d0-407e-9137-7902df0c2ab2" />
    </Tags>
    <RenderProxy AllowBakedRendering="1" />
  </Entity>
  <Entity Name="Steam_LINGER.steam_linger_2x1m_loop_1_gpu-011" Radius="0" Pos="-4.6775609999999999,-2.7810760000000001,-1.4460090000000001" Rotate="-0.5,0.5,0.5,-0.5" EntityClass="ParticleEffect" EntityClassGUID="8bb2877c-25d7-4832-97e1-e603ff8eba4b" EntityCryGUID="44ed88ca-11c0-c1b7-59b1-d791ee0cfd99" CastShadowMinSpec="1">
    <PropertiesDataCore>
      <EntityComponentParticleEffect __type="ParticleEffectParams" comment="empty" activate="1" spawnProbability="0.884477" primed="0" countPerUnit="0" attachType="None" attachForm="Vertices" registerByBbox="0" clipToVisArea="None" gpuVisAreaCullingMode="Default" forceDisableShadows="0" tesselationAmount="Default" attachToZone="Parent" seed="-1" renderLayer="Default">
        <particleEffect __type="GlobalResourceParticle" path="1df31750-d0f6-b35e-e40c-a1fdba7f8e4e|environments/generic/generic_steam_fx.Steam_RISE.steam_rise_2x1m_loop_1_gpu" />
        <scale __fullyInstanced="1" __baseType="CustomFloat" __type="FixedFloat" value="0.4" />
        <emissionSizeScale __type="Vec3" x="1.0" y="1.0" z="1.0" />
        <speedScale __fullyInstanced="1" __baseType="CustomFloat" __type="FixedFloat" value="1.0" />
        <timeScale __fullyInstanced="1" __baseType="CustomFloat" __type="RandomFloat" minimum="1.0" maximum="1.2" />
        <countScale __fullyInstanced="1" __baseType="CustomFloat" __type="FixedFloat" value="1.0" />
        <strength __fullyInstanced="1" __baseType="CustomFloat" __type="FixedFloat" value="-1.0" />
        <alphaScale __fullyInstanced="1" __baseType="CustomFloat" __type="FixedFloat" value="1.0" />
        <pulsePeriod __fullyInstanced="1" __baseType="CustomFloat" __type="FixedFloat" value="0.0" />
        <externalTint __fullyInstanced="1" __baseType="ParticleEffectNoneTintingParams" __type="ParticleEffectNoneTintingParams" />
        <audio __type="ParticleEffectAudioParams" enableAudio="1" isManagedAudioObject="0" attenuationScale="1.0" volume="0.0">
          <audioRTPC __type="AudioRtpc" rtpc="particlefx" />
        </audio>
        <gpuAudio __type="GPUParticleAudioStruct">
          <emissionStartTriggerOneShot __type="GlobalResourceAudio" audioTrigger="empty" />
          <emissionStopTriggerOneShot __type="GlobalResourceAudio" audioTrigger="empty" />
          <emissionStartTriggerLoop __type="GlobalResourceAudio" audioTrigger="empty" />
          <emissionStopTriggerLoop __type="GlobalResourceAudio" audioTrigger="empty" />
          <pulseDurationRtpc __type="AudioRtpc" rtpc="Particle_Pulse_Duration" />
          <normPulseTimeRtpc __type="AudioRtpc" rtpc="Particle_Normalized_Pulse_Time" />
          <strengthValRtpc __type="AudioRtpc" rtpc="Particle_Strength" />
          <scalingFactorRtpc __type="AudioRtpc" rtpc="Particle_ScalingFactor" />
        </gpuAudio>
      </EntityComponentParticleEffect>
    </PropertiesDataCore>
    <Tags>
      <Tag TagId="226a978c-41d0-407e-9137-7902df0c2ab2" />
    </Tags>
    <RenderProxy AllowBakedRendering="1" />
  </Entity>
  <Entity Name="Dust_Motes_ALL.dust_motes_4m3_loop_1-001" Radius="0" Pos="4.8151700000000002,-5.4031330000000004,-3.156066" Rotate="0.70710677,0.70710677,0,0" EntityClass="ParticleEffect" EntityClassGUID="8bb2877c-25d7-4832-97e1-e603ff8eba4b" EntityCryGUID="4d5d411c-3ea0-2efd-db6e-2d45a46b6380" CastShadowMinSpec="1">
    <PropertiesDataCore>
      <EntityComponentParticleEffect __type="ParticleEffectParams" comment="empty" activate="1" spawnProbability="1.0" primed="0" countPerUnit="0" attachType="None" attachForm="Vertices" registerByBbox="0" clipToVisArea="Local" gpuVisAreaCullingMode="Default" forceDisableShadows="0" tesselationAmount="Default" attachToZone="Parent" seed="-1" renderLayer="Default">
        <particleEffect __type="GlobalResourceParticle" path="b8bd8914-4e9c-e661-dcb9-e8284f06ef3a|environments/generic/generic_dust_fx.Dust_Motes_ALL.dust_motes_4m3_loop_1" />
        <scale __fullyInstanced="1" __baseType="CustomFloat" __type="FixedFloat" value="0.7" />
        <emissionSizeScale __type="Vec3" x="1.0" y="1.0" z="1.0" />
        <speedScale __fullyInstanced="1" __baseType="CustomFloat" __type="FixedFloat" value="1.0" />
        <timeScale __fullyInstanced="1" __baseType="CustomFloat" __type="FixedFloat" value="1.0" />
        <countScale __fullyInstanced="1" __baseType="CustomFloat" __type="RandomFloat" minimum="0.1" maximum="0.3" />
        <strength __fullyInstanced="1" __baseType="CustomFloat" __type="FixedFloat" value="-1.0" />
        <alphaScale __fullyInstanced="1" __baseType="CustomFloat" __type="FixedFloat" value="1.0" />
        <pulsePeriod __fullyInstanced="1" __baseType="CustomFloat" __type="FixedFloat" value="0.0" />
        <externalTint __fullyInstanced="1" __baseType="ParticleEffectNoneTintingParams" __type="ParticleEffectNoneTintingParams" />
        <audio __type="ParticleEffectAudioParams" enableAudio="1" isManagedAudioObject="0" attenuationScale="1.0" volume="0.0">
          <audioRTPC __type="AudioRtpc" rtpc="particlefx" />
        </audio>
        <gpuAudio __type="GPUParticleAudioStruct">
          <emissionStartTriggerOneShot __type="GlobalResourceAudio" audioTrigger="empty" />
          <emissionStopTriggerOneShot __type="GlobalResourceAudio" audioTrigger="empty" />
          <emissionStartTriggerLoop __type="GlobalResourceAudio" audioTrigger="empty" />
          <emissionStopTriggerLoop __type="GlobalResourceAudio" audioTrigger="empty" />
          <pulseDurationRtpc __type="AudioRtpc" rtpc="Particle_Pulse_Duration" />
          <normPulseTimeRtpc __type="AudioRtpc" rtpc="Particle_Normalized_Pulse_Time" />
          <strengthValRtpc __type="AudioRtpc" rtpc="Particle_Strength" />
          <scalingFactorRtpc __type="AudioRtpc" rtpc="Particle_ScalingFactor" />
        </gpuAudio>
      </EntityComponentParticleEffect>
    </PropertiesDataCore>
    <Tags>
      <Tag TagId="226a978c-41d0-407e-9137-7902df0c2ab2" />
    </Tags>
    <RenderProxy AllowBakedRendering="1" />
  </Entity>
  <Entity Name="Steam_FALL.steam_fall_1m_loop_1_gpu_decoupled-002" Radius="0" Pos="8.4062769999999993,-0.58808199999999999,-1.89642" Rotate="0.41061878,0.41061878,-0.57566673,0.57566673" EntityClass="ParticleEffect" EntityClassGUID="8bb2877c-25d7-4832-97e1-e603ff8eba4b" EntityCryGUID="4c1a3cd2-46b5-7ac2-e7b0-62efd0facd9c" CastShadowMinSpec="1">
    <PropertiesDataCore>
      <EntityComponentParticleEffect __type="ParticleEffectParams" comment="empty" activate="1" spawnProbability="1.0" primed="0" countPerUnit="0" attachType="None" attachForm="Vertices" registerByBbox="0" clipToVisArea="None" gpuVisAreaCullingMode="Default" forceDisableShadows="0" tesselationAmount="Default" attachToZone="Parent" seed="-1" renderLayer="Default">
        <particleEffect __type="GlobalResourceParticle" path="5bd346eb-2249-1b0c-aa01-f66f26aa72fe|environments/generic/generic_steam_fx.Steam_JET.steam_jet_2x16m_loop_1_gpu" />
        <scale __fullyInstanced="1" __baseType="CustomFloat" __type="FixedFloat" value="0.2" />
        <emissionSizeScale __type="Vec3" x="1.0" y="1.0" z="1.0" />
        <speedScale __fullyInstanced="1" __baseType="CustomFloat" __type="RandomFloat" minimum="1.4" maximum="1.8" />
        <timeScale __fullyInstanced="1" __baseType="CustomFloat" __type="FixedFloat" value="1.0" />
        <countScale __fullyInstanced="1" __baseType="CustomFloat" __type="FixedFloat" value="1.0" />
        <strength __fullyInstanced="1" __baseType="CustomFloat" __type="FixedFloat" value="-1.0" />
        <alphaScale __fullyInstanced="1" __baseType="CustomFloat" __type="FixedFloat" value="1.0" />
        <pulsePeriod __fullyInstanced="1" __baseType="CustomFloat" __type="FixedFloat" value="0.0" />
        <externalTint __fullyInstanced="1" __baseType="ParticleEffectNoneTintingParams" __type="ParticleEffectNoneTintingParams" />
        <audio __type="ParticleEffectAudioParams" enableAudio="1" isManagedAudioObject="0" attenuationScale="1.0" volume="0.0">
          <audioRTPC __type="AudioRtpc" rtpc="particlefx" />
        </audio>
        <gpuAudio __type="GPUParticleAudioStruct">
          <emissionStartTriggerOneShot __type="GlobalResourceAudio" audioTrigger="empty" />
          <emissionStopTriggerOneShot __type="GlobalResourceAudio" audioTrigger="empty" />
          <emissionStartTriggerLoop __type="GlobalResourceAudio" audioTrigger="empty" />
          <emissionStopTriggerLoop __type="GlobalResourceAudio" audioTrigger="empty" />
          <pulseDurationRtpc __type="AudioRtpc" rtpc="Particle_Pulse_Duration" />
          <normPulseTimeRtpc __type="AudioRtpc" rtpc="Particle_Normalized_Pulse_Time" />
          <strengthValRtpc __type="AudioRtpc" rtpc="Particle_Strength" />
          <scalingFactorRtpc __type="AudioRtpc" rtpc="Particle_ScalingFactor" />
        </gpuAudio>
      </EntityComponentParticleEffect>
    </PropertiesDataCore>
    <Tags>
      <Tag TagId="226a978c-41d0-407e-9137-7902df0c2ab2" />
    </Tags>
    <RenderProxy AllowBakedRendering="1" />
  </Entity>
  <Entity Name="LT_Sparks_Int.lt_sparks_int_gpu_2m_loop_constant-004" Radius="0" Pos="-3.7580710000000002,-4.1084269999999998,-3.08643" Rotate="0.5,0.5,-0.5,0.5" EntityClass="ParticleEffect" EntityClassGUID="8bb2877c-25d7-4832-97e1-e603ff8eba4b" EntityCryGUID="4a84a37c-4cbf-58f7-05f9-6f050cd8bb9b" CastShadowMinSpec="1">
    <PropertiesDataCore>
      <EntityComponentParticleEffect __type="ParticleEffectParams" comment="empty" activate="1" spawnProbability="1.0" primed="0" countPerUnit="0" attachType="None" attachForm="Vertices" registerByBbox="0" clipToVisArea="None" gpuVisAreaCullingMode="Default" forceDisableShadows="0" tesselationAmount="Default" attachToZone="Parent" seed="-1" renderLayer="Default">
        <particleEffect __type="GlobalResourceParticle" path="999352a2-ad9c-8dbe-5cab-7da3d7766df3|damage/lt_damage/lt_sparks_fx.LT_Sparks_Int.lt_sparks_int_gpu_1m_loop_constant" />
        <scale __fullyInstanced="1" __baseType="CustomFloat" __type="FixedFloat" value="0.5" />
        <emissionSizeScale __type="Vec3" x="1.0" y="1.0" z="1.0" />
        <speedScale __fullyInstanced="1" __baseType="CustomFloat" __type="FixedFloat" value="1.0" />
        <timeScale __fullyInstanced="1" __baseType="CustomFloat" __type="FixedFloat" value="1.0" />
        <countScale __fullyInstanced="1" __baseType="CustomFloat" __type="FixedFloat" value="1.0" />
        <strength __fullyInstanced="1" __baseType="CustomFloat" __type="FixedFloat" value="-1.0" />
        <alphaScale __fullyInstanced="1" __baseType="CustomFloat" __type="FixedFloat" value="1.0" />
        <pulsePeriod __fullyInstanced="1" __baseType="CustomFloat" __type="FixedFloat" value="0.0" />
        <externalTint __fullyInstanced="1" __baseType="ParticleEffectNoneTintingParams" __type="ParticleEffectNoneTintingParams" />
        <audio __type="ParticleEffectAudioParams" enableAudio="1" isManagedAudioObject="0" attenuationScale="1.0" volume="0.0">
          <audioRTPC __type="AudioRtpc" rtpc="particlefx" />
        </audio>
        <gpuAudio __type="GPUParticleAudioStruct">
          <emissionStartTriggerOneShot __type="GlobalResourceAudio" audioTrigger="empty" />
          <emissionStopTriggerOneShot __type="GlobalResourceAudio" audioTrigger="empty" />
          <emissionStartTriggerLoop __type="GlobalResourceAudio" audioTrigger="empty" />
          <emissionStopTriggerLoop __type="GlobalResourceAudio" audioTrigger="empty" />
          <pulseDurationRtpc __type="AudioRtpc" rtpc="Particle_Pulse_Duration" />
          <normPulseTimeRtpc __type="AudioRtpc" rtpc="Particle_Normalized_Pulse_Time" />
          <strengthValRtpc __type="AudioRtpc" rtpc="Particle_Strength" />
          <scalingFactorRtpc __type="AudioRtpc" rtpc="Particle_ScalingFactor" />
        </gpuAudio>
      </EntityComponentParticleEffect>
    </PropertiesDataCore>
    <Tags>
      <Tag TagId="226a978c-41d0-407e-9137-7902df0c2ab2" />
    </Tags>
    <RenderProxy AllowBakedRendering="1" />
  </Entity>
</Entities>